rtl/adder.sv
module adder #(
    parameter N = 8                // Width of the adder
)(
    input  logic [N-1:0] a,        // Input A
    input  logic [N-1:0] b,        // Input B
    output logic [N-1:0] sum,      // Sum output
    output logic        carry      // Carry-out
);

    logic [N:0] result;

    always_comb begin
        result = a + b;
        sum    = result[N-1:0];
        carry  = result[N];
    
     // ✅ Verilator-compatible assertions
    assert (sum == result[N-1:0])
      else $error("❌ Sum mismatch: a=%0h b=%0h sum=%0h expected=%0h", a, b, sum, result[N-1:0]);

    assert (carry == result[N])
      else $error("❌ Carry mismatch: a=%0h b=%0h carry=%0b expected=%0b", a, b, carry, result[N]);
  end

endmodule

dump.vcd
$version Generated by VerilatedVcd $end
$timescale 1ps $end
 $scope module TOP $end
  $var wire 8 # a [7:0] $end
  $var wire 8 $ b [7:0] $end
  $var wire 8 % sum [7:0] $end
  $var wire 1 & carry $end
  $scope module adder $end
   $var wire 32 ( N [31:0] $end
   $var wire 8 # a [7:0] $end
   $var wire 8 $ b [7:0] $end
   $var wire 8 % sum [7:0] $end
   $var wire 1 & carry $end
   $var wire 9 ' result [8:0] $end
  $upscope $end
 $upscope $end
$enddefinitions $end


#0
b00000000 #
b00000000 $
b00000000 %
0&
b000000000 '
b00000000000000000000000000001000 (
#1
b00101001 #
b00100011 $
b01001100 %
b001001100 '
#3
b10111110 #
b10000100 $
b01000010 %
1&
b101000010 '
#5
b11100001 #
b01101100 $
b01001101 %
b101001101 '
#7
b11010110 #
b10101110 $
b10000100 %
b110000100 '
#9
b01010010 #
b10010000 $
b11100010 %
0&
b011100010 '
#11
b01001001 #
b11110001 $
b00111010 %
1&
b100111010 '
#13
b11110001 #
b10111011 $
b10101100 %
b110101100 '
#15
b11101001 #
b11101011 $
b11010100 %
b111010100 '
#17
b10110011 #
b10100110 $
b01011001 %
b101011001 '
#19
b11011011 #
b00111100 $
b00010111 %
b100010111 '
#21
b10000111 #
b00001100 $
b10010011 %
0&
b010010011 '
#23
b00111110 #
b10011001 $
b11010111 %
b011010111 '
#25
b00100100 #
b01011110 $
b10000010 %
b010000010 '
#27
b00001101 #
b00011100 $
b00101001 %
b000101001 '
#29
b00000110 #
b10110111 $
b10111101 %
b010111101 '
#31
b01000111 #
b11011110 $
b00100101 %
1&
b100100101 '
#33
b10110011 #
b00010010 $
b11000101 %
0&
b011000101 '
#35
b01001101 #
b11001000 $
b00010101 %
1&
b100010101 '
#37
b01000011 #
b10111011 $
b11111110 %
0&
b011111110 '
#39
b10001011 #
b10100110 $
b00110001 %
1&
b100110001 '
#41
b00011111 #
b00000011 $
b00100010 %
0&
b000100010 '
#43
b01011010 #
b01111101 $
b11010111 %
b011010111 '
#45
b00001001 #
b00111000 $
b01000001 %
b001000001 '
#47
b00100101 #
b00011111 $
b01000100 %
b001000100 '
#49
b01011101 #
b11010100 $
b00110001 %
1&
b100110001 '
#51
b11001011 #
b11111100 $
b11000111 %
b111000111 '
#53
b10010110 #
b11110101 $
b10001011 %
b110001011 '
#55
b01000101 #
b00111011 $
b10000000 %
0&
b010000000 '
#57
b00010011 #
b00001101 $
b00100000 %
b000100000 '
#59
b10001001 #
b00001010 $
b10010011 %
b010010011 '
#61
b00011100 #
b11011011 $
b11110111 %
b011110111 '
#63
b10101110 #
b00110010 $
b11100000 %
b011100000 '
#65
b00100000 #
b10011010 $
b10111010 %
b010111010 '
#67
b01010000 #
b11101110 $
b00111110 %
1&
b100111110 '
#69
b01000000 #
b01111000 $
b10111000 %
0&
b010111000 '
#71
b00110110 #
b11111101 $
b00110011 %
1&
b100110011 '
#73
b00010010 #
b01001001 $
b01011011 %
0&
b001011011 '
#75
b00110010 #
b11110110 $
b00101000 %
1&
b100101000 '
#77
b10011110 #
b01111101 $
b00011011 %
b100011011 '
#79
b01001001 #
b11011100 $
b00100101 %
b100100101 '
#81
b10101101 #
b01001111 $
b11111100 %
0&
b011111100 '
#83
b00010100 #
b11110010 $
b00000110 %
1&
b100000110 '
#85
b01000100 #
b01000000 $
b10000100 %
0&
b010000100 '
#87
b01100110 #
b11010000 $
b00110110 %
1&
b100110110 '
#89
b01101011 #
b11000100 $
b00101111 %
b100101111 '
#91
b00110000 #
b10110111 $
b11100111 %
0&
b011100111 '
#93
b00110010 #
b00111011 $
b01101101 %
b001101101 '
#95
b10100001 #
b00100010 $
b11000011 %
b011000011 '
#97
b11110110 #
b00011000 %
1&
b100011000 '
#99
b10010001 #
b10011101 $
b00101110 %
b100101110 '
